petsird/__init__.py
petsird/helpers/__init__.py
petsird_helpers-0.0.0.dist-info/METADATA
petsird_helpers-0.0.0.dist-info/WHEEL
petsird_helpers-0.0.0.dist-info/top_level.txt
petsird_helpers-0.0.0.dist-info/RECORD
